mypackage/__init__.py
mypackage/mypackage.py
mVedrmypackage-0.0.3.dist-info/METADATA
mVedrmypackage-0.0.3.dist-info/WHEEL
mVedrmypackage-0.0.3.dist-info/top_level.txt
mVedrmypackage-0.0.3.dist-info/RECORD
